shrinkix/__init__.py
shrinkix/__main__.py
shrinkix/cli.py
shrinkix/info.py
shrinkix/py.typed
shrinkix/shrinker.py
shrinkix/utils.py
shrinkix-1.1.1.dist-info/METADATA
shrinkix-1.1.1.dist-info/WHEEL
shrinkix-1.1.1.dist-info/entry_points.txt
shrinkix-1.1.1.dist-info/licenses/LICENSE
shrinkix-1.1.1.dist-info/RECORD
