Metadata-Version: 2.4
Name: shrinkix
Version: 1.1.1
Summary: Reduces the size of images for the web.
Project-URL: Homepage, https://github.com/Dashstrom/shrinkix
Project-URL: Issues, https://github.com/Dashstrom/shrinkix/issues
Project-URL: Documentation, https://dashstrom.github.io/shrinkix
Project-URL: Source, https://github.com/Dashstrom/shrinkix
Author-email: Dashstrom <dashstrom.pro@gmail.com>
Maintainer-email: Dashstrom <dashstrom.pro@gmail.com>
License-Expression: MIT
License-File: LICENSE
Keywords: cli,color-reduction,image,optimizer,python,reduce
Classifier: Development Status :: 5 - Production/Stable
Classifier: Environment :: Console
Classifier: Intended Audience :: Developers
Classifier: Intended Audience :: System Administrators
Classifier: Natural Language :: English
Classifier: Operating System :: OS Independent
Classifier: Programming Language :: Python :: 3
Classifier: Programming Language :: Python :: 3 :: Only
Classifier: Programming Language :: Python :: 3.10
Classifier: Programming Language :: Python :: 3.11
Classifier: Programming Language :: Python :: 3.12
Classifier: Programming Language :: Python :: 3.13
Classifier: Typing :: Typed
Requires-Python: <4.0,>=3.10
Requires-Dist: numpy>=1.22.0
Requires-Dist: piexif>=1.0.0
Requires-Dist: pillow>=11.0.0
Requires-Dist: scikit-learn>=1.1.0
Requires-Dist: tqdm>=4.1.0
